{
    "info": {
        "contact": {
            "email": "dev-platform@stripe.com",
            "name": "Stripe Dev Platform Team",
            "url": "https://stripe.com"
        },
        "description": "The Stripe REST API. Please see https://stripe.com/docs/api for more details.",
        "termsOfService": "https://stripe.com/us/terms/",
        "title": "Stripe API",
        "version": "2023-08-16",
        "x-stripeSpecFilename": "spec3"
    },
    "openapi": "3.0.0",
    "paths": {
        "/v1/files/{file}": {
            "get": {
                "description": "<p>Retrieves the details of an existing file object. Supply the unique file ID from a file, and Stripe will return the corresponding file object. To access file contents, see the <a href=\"/docs/file-upload#download-file-contents\">File Upload Guide</a>.</p>",
                "operationId": "GetFilesFile",
                "parameters": [
                    {
                        "description": "Specifies which fields in the response should be expanded.",
                        "explode": true,
                        "in": "query",
                        "name": "expand",
                        "required": false,
                        "schema": {
                            "items": { "maxLength": 5000, "type": "string" },
                            "type": "array"
                        },
                        "style": "deepObject"
                    },
                    {
                        "in": "path",
                        "name": "file",
                        "required": true,
                        "schema": { "maxLength": 5000, "type": "string" },
                        "style": "simple"
                    }
                ],
                "requestBody": {
                    "content": {
                        "application/x-www-form-urlencoded": {
                            "encoding": {},
                            "schema": {
                                "additionalProperties": false,
                                "properties": {},
                                "type": "object"
                            }
                        }
                    },
                    "required": false
                },
                "responses": {
                    "200": {
                        "content": {
                            "application/json": {
                                "schema": {
                                    "description": "This is an object representing a file hosted on Stripe's servers. The\nfile may have been uploaded by yourself using the [create file](https://stripe.com/docs/api#create_file)\nrequest (for example, when uploading dispute evidence) or it may have\nbeen created by Stripe (for example, the results of a [Sigma scheduled\nquery](#scheduled_queries)).\n\nRelated guide: [File upload guide](https://stripe.com/docs/file-upload)",
                                    "properties": {
                                        "created": {
                                            "description": "Time at which the object was created. Measured in seconds since the Unix epoch.",
                                            "format": "unix-time",
                                            "type": "integer"
                                        },
                                        "expires_at": {
                                            "description": "The time at which the file expires and is no longer available in epoch seconds.",
                                            "format": "unix-time",
                                            "nullable": true,
                                            "type": "integer"
                                        },
                                        "filename": {
                                            "description": "A filename for the file, suitable for saving to a filesystem.",
                                            "maxLength": 5000,
                                            "nullable": true,
                                            "type": "string"
                                        },
                                        "id": {
                                            "description": "Unique identifier for the object.",
                                            "maxLength": 5000,
                                            "type": "string"
                                        },
                                        "links": {
                                            "description": "A list of [file links](https://stripe.com/docs/api#file_links) that point at this file.",
                                            "nullable": true,
                                            "properties": {
                                                "data": {
                                                    "description": "Details about each object.",
                                                    "items": {
                                                        "description": "To share the contents of a `File` object with non-Stripe users, you can\ncreate a `FileLink`. `FileLink`s contain a URL that can be used to\nretrieve the contents of the file without authentication.",
                                                        "properties": {
                                                            "created": {
                                                                "description": "Time at which the object was created. Measured in seconds since the Unix epoch.",
                                                                "format": "unix-time",
                                                                "type": "integer"
                                                            },
                                                            "expired": {
                                                                "description": "Whether this link is already expired.",
                                                                "type": "boolean"
                                                            },
                                                            "expires_at": {
                                                                "description": "Time at which the link expires.",
                                                                "format": "unix-time",
                                                                "nullable": true,
                                                                "type": "integer"
                                                            },
                                                            "file": {
                                                                "anyOf": [
                                                                    {
                                                                        "maxLength": 5000,
                                                                        "type": "string"
                                                                    },
                                                                    {}
                                                                ],
                                                                "description": "The file object this link points to.",
                                                                "x-expansionResources": {
                                                                    "oneOf": [
                                                                        {}
                                                                    ]
                                                                }
                                                            },
                                                            "id": {
                                                                "description": "Unique identifier for the object.",
                                                                "maxLength": 5000,
                                                                "type": "string"
                                                            },
                                                            "livemode": {
                                                                "description": "Has the value `true` if the object exists in live mode or the value `false` if the object exists in test mode.",
                                                                "type": "boolean"
                                                            },
                                                            "metadata": {
                                                                "additionalProperties": {
                                                                    "maxLength": 500,
                                                                    "type": "string"
                                                                },
                                                                "description": "Set of [key-value pairs](https://stripe.com/docs/api/metadata) that you can attach to an object. This can be useful for storing additional information about the object in a structured format.",
                                                                "type": "object"
                                                            },
                                                            "object": {
                                                                "description": "String representing the object's type. Objects of the same type share the same value.",
                                                                "enum": [
                                                                    "file_link"
                                                                ],
                                                                "type": "string"
                                                            },
                                                            "url": {
                                                                "description": "The publicly accessible URL to download the file.",
                                                                "maxLength": 5000,
                                                                "nullable": true,
                                                                "type": "string"
                                                            }
                                                        },
                                                        "required": [
                                                            "created",
                                                            "expired",
                                                            "file",
                                                            "id",
                                                            "livemode",
                                                            "metadata",
                                                            "object"
                                                        ],
                                                        "title": "FileLink",
                                                        "type": "object",
                                                        "x-expandableFields": [
                                                            "file"
                                                        ],
                                                        "x-resourceId": "file_link"
                                                    },
                                                    "type": "array"
                                                },
                                                "has_more": {
                                                    "description": "True if this list has another page of items after this one that can be fetched.",
                                                    "type": "boolean"
                                                },
                                                "object": {
                                                    "description": "String representing the object's type. Objects of the same type share the same value. Always has the value `list`.",
                                                    "enum": ["list"],
                                                    "type": "string"
                                                },
                                                "url": {
                                                    "description": "The URL where this list can be accessed.",
                                                    "maxLength": 5000,
                                                    "pattern": "^/v1/file_links",
                                                    "type": "string"
                                                }
                                            },
                                            "required": [
                                                "data",
                                                "has_more",
                                                "object",
                                                "url"
                                            ],
                                            "title": "FileFileLinkList",
                                            "type": "object",
                                            "x-expandableFields": ["data"]
                                        },
                                        "object": {
                                            "description": "String representing the object's type. Objects of the same type share the same value.",
                                            "enum": ["file"],
                                            "type": "string"
                                        },
                                        "purpose": {
                                            "description": "The [purpose](https://stripe.com/docs/file-upload#uploading-a-file) of the uploaded file.",
                                            "enum": [
                                                "account_requirement",
                                                "additional_verification",
                                                "business_icon",
                                                "business_logo",
                                                "customer_signature",
                                                "dispute_evidence",
                                                "document_provider_identity_document",
                                                "finance_report_run",
                                                "identity_document",
                                                "identity_document_downloadable",
                                                "pci_document",
                                                "selfie",
                                                "sigma_scheduled_query",
                                                "tax_document_user_upload",
                                                "terminal_reader_splashscreen"
                                            ],
                                            "type": "string",
                                            "x-stripeBypassValidation": true
                                        },
                                        "size": {
                                            "description": "The size in bytes of the file object.",
                                            "type": "integer"
                                        },
                                        "title": {
                                            "description": "A user friendly title for the document.",
                                            "maxLength": 5000,
                                            "nullable": true,
                                            "type": "string"
                                        },
                                        "type": {
                                            "description": "The type of the file returned (e.g., `csv`, `pdf`, `jpg`, or `png`).",
                                            "maxLength": 5000,
                                            "nullable": true,
                                            "type": "string"
                                        },
                                        "url": {
                                            "description": "The URL from which the file can be downloaded using your live secret API key.",
                                            "maxLength": 5000,
                                            "nullable": true,
                                            "type": "string"
                                        }
                                    },
                                    "required": [
                                        "created",
                                        "id",
                                        "object",
                                        "purpose",
                                        "size"
                                    ],
                                    "title": "File",
                                    "type": "object",
                                    "x-expandableFields": ["links"],
                                    "x-resourceId": "file"
                                }
                            }
                        },
                        "description": "Successful response."
                    },
                    "default": {
                        "content": {
                            "application/json": {
                                "schema": "#/components/schemas/error"
                            }
                        },
                        "description": "Error response."
                    }
                }
            }
        }
    },
    "security": [{ "basicAuth": [] }, { "bearerAuth": [] }],
    "servers": [{ "url": "https://api.stripe.com/" }]
}
